cli.py
osu_cleaner_cli_mod-0.0.9.dist-info/licenses/LICENSE
osu_cleaner_cli_mod-0.0.9.dist-info/METADATA
osu_cleaner_cli_mod-0.0.9.dist-info/WHEEL
osu_cleaner_cli_mod-0.0.9.dist-info/entry_points.txt
osu_cleaner_cli_mod-0.0.9.dist-info/top_level.txt
osu_cleaner_cli_mod-0.0.9.dist-info/RECORD
