Metadata-Version: 2.4
Name: osu_cleaner_cli-mod
Version: 0.0.9
Summary: Remove unwanted files from osu! Songs directory. Modified Version
Home-page: https://github.com/miyuki-ts/osu-cleaner-cli-mod
Author: Layerex
Author-email: layerex@dismail.de
Classifier: Development Status :: 6 - Mature
Classifier: Programming Language :: Python :: 3
Classifier: License :: OSI Approved :: GNU General Public License v3 (GPLv3)
Classifier: Operating System :: OS Independent
Classifier: Topic :: Utilities
License-File: LICENSE
Dynamic: author
Dynamic: author-email
Dynamic: classifier
Dynamic: description
Dynamic: description-content-type
Dynamic: home-page
Dynamic: license-file
Dynamic: summary
